{
    "manifestVersion": 1,
    "id": "pull-request-tools",
    "name": "Pull Request Quality Check Tools",
    "version": "0.3.8",
    "publisher": "PNIMedia",
    "targets": [
        {
            "id": "Microsoft.VisualStudio.Services"
        }
    ],    
    "description": "Tools for checking pull requests' quality. Includes report of code coverage changes.",
    "categories": [
        "Azure Pipelines"
    ],
    "files": [
        {
            "path": "buildAndReleaseTask"
        }
    ],
    "contributions": [
        {
            "id": "report-code-coverage",
            "type": "ms.vss-distributed-task.task",
            "targets": [
                "ms.vss-distributed-task.tasks"
            ],
            "properties": {
                "name": "buildAndReleaseTask"
            }
        }
    ]
}